{
	"tables": [
		{
			"key": "autoinckeywordtest",
			"schema": "",
			"name": "autoinckeywordtest",
			"columns": [
				{
					"name": "id",
					"db_type": "INTEGER",
					"default": "auto_increment",
					"comment": "",
					"nullable": false,
					"generated": false,
					"autoincr": false,
					"domain_name": "",
					"type": "int32"
				},
				{
					"name": "user_id",
					"db_type": "INT",
					"default": "",
					"comment": "",
					"nullable": false,
					"generated": false,
					"autoincr": false,
					"domain_name": "",
					"type": "int32"
				},
				{
					"name": "sponsor_id",
					"db_type": "INT",
					"default": "NULL",
					"comment": "",
					"nullable": true,
					"generated": false,
					"autoincr": false,
					"domain_name": "",
					"type": "int32"
				},
				{
					"name": "something",
					"db_type": "TEXT",
					"default": "NULL",
					"comment": "",
					"nullable": true,
					"generated": false,
					"autoincr": false,
					"domain_name": "",
					"type": "string"
				},
				{
					"name": "another",
					"db_type": "TEXT",
					"default": "NULL",
					"comment": "",
					"nullable": true,
					"generated": false,
					"autoincr": false,
					"domain_name": "",
					"type": "string"
				}
			],
			"constraints": {
				"primary": {
					"name": "pk_main_autoinckeywordtest",
					"columns": [
						"id"
					]
				},
				"foreign": [
					{
						"name": "fk_autoinckeywordtest_0",
						"columns": [
							"user_id",
							"sponsor_id"
						],
						"foreign_table": "videos",
						"foreign_columns": [
							"user_id",
							"sponsor_id"
						]
					}
				],
				"uniques": [
					{
						"name": "sqlite_autoindex_autoinckeywordtest_2",
						"columns": [
							"something",
							"another"
						]
					},
					{
						"name": "sqlite_autoindex_autoinckeywordtest_1",
						"columns": [
							"sponsor_id"
						]
					}
				]
			}
		},
		{
			"key": "autoinctest",
			"schema": "",
			"name": "autoinctest",
			"columns": [
				{
					"name": "id",
					"db_type": "INTEGER",
					"default": "auto_increment",
					"comment": "",
					"nullable": false,
					"generated": false,
					"autoincr": false,
					"domain_name": "",
					"type": "int32"
				}
			],
			"constraints": {
				"primary": {
					"name": "pk_main_autoinctest",
					"columns": [
						"id"
					]
				},
				"foreign": [
					{
						"name": "fk_autoinctest_0",
						"columns": [
							"id"
						],
						"foreign_table": "tags",
						"foreign_columns": [
							"id"
						]
					}
				],
				"uniques": []
			}
		},
		{
			"key": "has_generated_columns",
			"schema": "",
			"name": "has_generated_columns",
			"columns": [
				{
					"name": "a",
					"db_type": "INTEGER",
					"default": "auto_increment",
					"comment": "",
					"nullable": false,
					"generated": false,
					"autoincr": false,
					"domain_name": "",
					"type": "int32"
				},
				{
					"name": "b",
					"db_type": "INT",
					"default": "NULL",
					"comment": "",
					"nullable": true,
					"generated": false,
					"autoincr": false,
					"domain_name": "",
					"type": "int32"
				},
				{
					"name": "c",
					"db_type": "TEXT",
					"default": "NULL",
					"comment": "",
					"nullable": true,
					"generated": false,
					"autoincr": false,
					"domain_name": "",
					"type": "string"
				},
				{
					"name": "d",
					"db_type": "INT",
					"default": "auto_generated",
					"comment": "",
					"nullable": true,
					"generated": true,
					"autoincr": false,
					"domain_name": "",
					"type": "int32"
				},
				{
					"name": "e",
					"db_type": "TEXT",
					"default": "auto_generated",
					"comment": "",
					"nullable": true,
					"generated": true,
					"autoincr": false,
					"domain_name": "",
					"type": "string"
				}
			],
			"constraints": {
				"primary": {
					"name": "pk_main_has_generated_columns",
					"columns": [
						"a"
					]
				},
				"foreign": [],
				"uniques": []
			}
		},
		{
			"key": "one.as_generated_columns",
			"schema": "one",
			"name": "as_generated_columns",
			"columns": [
				{
					"name": "a",
					"db_type": "INTEGER",
					"default": "auto_increment",
					"comment": "",
					"nullable": false,
					"generated": false,
					"autoincr": false,
					"domain_name": "",
					"type": "int32"
				},
				{
					"name": "b",
					"db_type": "INT",
					"default": "NULL",
					"comment": "",
					"nullable": true,
					"generated": false,
					"autoincr": false,
					"domain_name": "",
					"type": "int32"
				},
				{
					"name": "c",
					"db_type": "TEXT",
					"default": "NULL",
					"comment": "",
					"nullable": true,
					"generated": false,
					"autoincr": false,
					"domain_name": "",
					"type": "string"
				},
				{
					"name": "d",
					"db_type": "INT",
					"default": "auto_generated",
					"comment": "",
					"nullable": true,
					"generated": true,
					"autoincr": false,
					"domain_name": "",
					"type": "int32"
				},
				{
					"name": "e",
					"db_type": "TEXT",
					"default": "auto_generated",
					"comment": "",
					"nullable": true,
					"generated": true,
					"autoincr": false,
					"domain_name": "",
					"type": "string"
				}
			],
			"constraints": {
				"primary": {
					"name": "pk_one_as_generated_columns",
					"columns": [
						"a"
					]
				},
				"foreign": [],
				"uniques": []
			}
		},
		{
			"key": "one.autoinckeywordtest",
			"schema": "one",
			"name": "autoinckeywordtest",
			"columns": [
				{
					"name": "id",
					"db_type": "INTEGER",
					"default": "auto_increment",
					"comment": "",
					"nullable": false,
					"generated": false,
					"autoincr": false,
					"domain_name": "",
					"type": "int32"
				},
				{
					"name": "b",
					"db_type": "INTEGER",
					"default": "NULL",
					"comment": "",
					"nullable": true,
					"generated": false,
					"autoincr": false,
					"domain_name": "",
					"type": "int32"
				}
			],
			"constraints": {
				"primary": {
					"name": "pk_one_autoinckeywordtest",
					"columns": [
						"id"
					]
				},
				"foreign": [],
				"uniques": []
			}
		},
		{
			"key": "one.autoinctest",
			"schema": "one",
			"name": "autoinctest",
			"columns": [
				{
					"name": "id",
					"db_type": "INTEGER",
					"default": "auto_increment",
					"comment": "",
					"nullable": false,
					"generated": false,
					"autoincr": false,
					"domain_name": "",
					"type": "int32"
				}
			],
			"constraints": {
				"primary": {
					"name": "pk_one_autoinctest",
					"columns": [
						"id"
					]
				},
				"foreign": [],
				"uniques": []
			}
		},
		{
			"key": "one.sponsors",
			"schema": "one",
			"name": "sponsors",
			"columns": [
				{
					"name": "id",
					"db_type": "INT",
					"default": "",
					"comment": "",
					"nullable": false,
					"generated": false,
					"autoincr": false,
					"domain_name": "",
					"type": "int32"
				}
			],
			"constraints": {
				"primary": {
					"name": "pk_one_sponsors",
					"columns": [
						"id"
					]
				},
				"foreign": [],
				"uniques": []
			}
		},
		{
			"key": "one.tags",
			"schema": "one",
			"name": "tags",
			"columns": [
				{
					"name": "id",
					"db_type": "INT",
					"default": "",
					"comment": "",
					"nullable": false,
					"generated": false,
					"autoincr": false,
					"domain_name": "",
					"type": "int32"
				}
			],
			"constraints": {
				"primary": {
					"name": "pk_one_tags",
					"columns": [
						"id"
					]
				},
				"foreign": [],
				"uniques": []
			}
		},
		{
			"key": "one.user_videos",
			"schema": "one",
			"name": "user_videos",
			"columns": [
				{
					"name": "user_id",
					"db_type": "INT",
					"default": "NULL",
					"comment": "",
					"nullable": true,
					"generated": false,
					"autoincr": false,
					"domain_name": "",
					"type": "int32"
				},
				{
					"name": "video_id",
					"db_type": "INT",
					"default": "NULL",
					"comment": "",
					"nullable": true,
					"generated": false,
					"autoincr": false,
					"domain_name": "",
					"type": "int32"
				},
				{
					"name": "sponsor_id",
					"db_type": "INT",
					"default": "NULL",
					"comment": "",
					"nullable": true,
					"generated": false,
					"autoincr": false,
					"domain_name": "",
					"type": "int32"
				}
			],
			"constraints": {
				"primary": null,
				"foreign": [],
				"uniques": []
			}
		},
		{
			"key": "one.users",
			"schema": "one",
			"name": "users",
			"columns": [
				{
					"name": "id",
					"db_type": "INT",
					"default": "",
					"comment": "",
					"nullable": false,
					"generated": false,
					"autoincr": false,
					"domain_name": "",
					"type": "int32"
				}
			],
			"constraints": {
				"primary": {
					"name": "pk_one_users",
					"columns": [
						"id"
					]
				},
				"foreign": [],
				"uniques": []
			}
		},
		{
			"key": "one.video_tags",
			"schema": "one",
			"name": "video_tags",
			"columns": [
				{
					"name": "video_id",
					"db_type": "INT",
					"default": "",
					"comment": "",
					"nullable": false,
					"generated": false,
					"autoincr": false,
					"domain_name": "",
					"type": "int32"
				},
				{
					"name": "tag_id",
					"db_type": "INT",
					"default": "",
					"comment": "",
					"nullable": false,
					"generated": false,
					"autoincr": false,
					"domain_name": "",
					"type": "int32"
				}
			],
			"constraints": {
				"primary": {
					"name": "pk_one_video_tags",
					"columns": [
						"video_id",
						"tag_id"
					]
				},
				"foreign": [
					{
						"name": "fk_video_tags_0",
						"columns": [
							"tag_id"
						],
						"foreign_table": "one.tags",
						"foreign_columns": [
							"id"
						]
					},
					{
						"name": "fk_video_tags_1",
						"columns": [
							"video_id"
						],
						"foreign_table": "one.videos",
						"foreign_columns": [
							"id"
						]
					}
				],
				"uniques": []
			}
		},
		{
			"key": "one.videos",
			"schema": "one",
			"name": "videos",
			"columns": [
				{
					"name": "id",
					"db_type": "INT",
					"default": "",
					"comment": "",
					"nullable": false,
					"generated": false,
					"autoincr": false,
					"domain_name": "",
					"type": "int32"
				},
				{
					"name": "user_id",
					"db_type": "INT",
					"default": "",
					"comment": "",
					"nullable": false,
					"generated": false,
					"autoincr": false,
					"domain_name": "",
					"type": "int32"
				},
				{
					"name": "sponsor_id",
					"db_type": "INT",
					"default": "NULL",
					"comment": "",
					"nullable": true,
					"generated": false,
					"autoincr": false,
					"domain_name": "",
					"type": "int32"
				}
			],
			"constraints": {
				"primary": {
					"name": "pk_one_videos",
					"columns": [
						"id"
					]
				},
				"foreign": [
					{
						"name": "fk_videos_0",
						"columns": [
							"sponsor_id"
						],
						"foreign_table": "one.sponsors",
						"foreign_columns": [
							"id"
						]
					},
					{
						"name": "fk_videos_1",
						"columns": [
							"user_id"
						],
						"foreign_table": "one.users",
						"foreign_columns": [
							"id"
						]
					}
				],
				"uniques": [
					{
						"name": "sqlite_autoindex_videos_2",
						"columns": [
							"sponsor_id"
						]
					}
				]
			}
		},
		{
			"key": "sponsors",
			"schema": "",
			"name": "sponsors",
			"columns": [
				{
					"name": "id",
					"db_type": "INT",
					"default": "",
					"comment": "",
					"nullable": false,
					"generated": false,
					"autoincr": false,
					"domain_name": "",
					"type": "int32"
				}
			],
			"constraints": {
				"primary": {
					"name": "pk_main_sponsors",
					"columns": [
						"id"
					]
				},
				"foreign": [],
				"uniques": []
			}
		},
		{
			"key": "tags",
			"schema": "",
			"name": "tags",
			"columns": [
				{
					"name": "id",
					"db_type": "INT",
					"default": "",
					"comment": "",
					"nullable": false,
					"generated": false,
					"autoincr": false,
					"domain_name": "",
					"type": "int32"
				}
			],
			"constraints": {
				"primary": {
					"name": "pk_main_tags",
					"columns": [
						"id"
					]
				},
				"foreign": [],
				"uniques": []
			}
		},
		{
			"key": "type_monsters",
			"schema": "",
			"name": "type_monsters",
			"columns": [
				{
					"name": "id",
					"db_type": "INT",
					"default": "",
					"comment": "",
					"nullable": false,
					"generated": false,
					"autoincr": false,
					"domain_name": "",
					"type": "int32"
				},
				{
					"name": "id_two",
					"db_type": "INT",
					"default": "",
					"comment": "",
					"nullable": false,
					"generated": false,
					"autoincr": false,
					"domain_name": "",
					"type": "int32"
				},
				{
					"name": "id_three",
					"db_type": "INT",
					"default": "NULL",
					"comment": "",
					"nullable": true,
					"generated": false,
					"autoincr": false,
					"domain_name": "",
					"type": "int32"
				},
				{
					"name": "bool_zero",
					"db_type": "BOOL",
					"default": "NULL",
					"comment": "",
					"nullable": true,
					"generated": false,
					"autoincr": false,
					"domain_name": "",
					"type": "string"
				},
				{
					"name": "bool_one",
					"db_type": "BOOL",
					"default": "NULL",
					"comment": "",
					"nullable": true,
					"generated": false,
					"autoincr": false,
					"domain_name": "",
					"type": "string"
				},
				{
					"name": "bool_two",
					"db_type": "BOOL",
					"default": "",
					"comment": "",
					"nullable": false,
					"generated": false,
					"autoincr": false,
					"domain_name": "",
					"type": "string"
				},
				{
					"name": "bool_three",
					"db_type": "BOOL",
					"default": "false",
					"comment": "",
					"nullable": true,
					"generated": false,
					"autoincr": false,
					"domain_name": "",
					"type": "string"
				},
				{
					"name": "bool_four",
					"db_type": "BOOL",
					"default": "true",
					"comment": "",
					"nullable": true,
					"generated": false,
					"autoincr": false,
					"domain_name": "",
					"type": "string"
				},
				{
					"name": "bool_five",
					"db_type": "BOOL",
					"default": "false",
					"comment": "",
					"nullable": false,
					"generated": false,
					"autoincr": false,
					"domain_name": "",
					"type": "string"
				},
				{
					"name": "bool_six",
					"db_type": "BOOL",
					"default": "true",
					"comment": "",
					"nullable": false,
					"generated": false,
					"autoincr": false,
					"domain_name": "",
					"type": "string"
				},
				{
					"name": "string_zero",
					"db_type": "VARCHAR(1)",
					"default": "NULL",
					"comment": "",
					"nullable": true,
					"generated": false,
					"autoincr": false,
					"domain_name": "",
					"type": "string"
				},
				{
					"name": "string_one",
					"db_type": "VARCHAR(1)",
					"default": "NULL",
					"comment": "",
					"nullable": true,
					"generated": false,
					"autoincr": false,
					"domain_name": "",
					"type": "string"
				},
				{
					"name": "string_two",
					"db_type": "VARCHAR(1)",
					"default": "",
					"comment": "",
					"nullable": false,
					"generated": false,
					"autoincr": false,
					"domain_name": "",
					"type": "string"
				},
				{
					"name": "string_three",
					"db_type": "VARCHAR(1)",
					"default": "'a'",
					"comment": "",
					"nullable": true,
					"generated": false,
					"autoincr": false,
					"domain_name": "",
					"type": "string"
				},
				{
					"name": "string_four",
					"db_type": "VARCHAR(1)",
					"default": "'b'",
					"comment": "",
					"nullable": false,
					"generated": false,
					"autoincr": false,
					"domain_name": "",
					"type": "string"
				},
				{
					"name": "string_five",
					"db_type": "VARCHAR(1000)",
					"default": "NULL",
					"comment": "",
					"nullable": true,
					"generated": false,
					"autoincr": false,
					"domain_name": "",
					"type": "string"
				},
				{
					"name": "string_six",
					"db_type": "VARCHAR(1000)",
					"default": "NULL",
					"comment": "",
					"nullable": true,
					"generated": false,
					"autoincr": false,
					"domain_name": "",
					"type": "string"
				},
				{
					"name": "string_seven",
					"db_type": "VARCHAR(1000)",
					"default": "",
					"comment": "",
					"nullable": false,
					"generated": false,
					"autoincr": false,
					"domain_name": "",
					"type": "string"
				},
				{
					"name": "string_eight",
					"db_type": "VARCHAR(1000)",
					"default": "'abcdefgh'",
					"comment": "",
					"nullable": true,
					"generated": false,
					"autoincr": false,
					"domain_name": "",
					"type": "string"
				},
				{
					"name": "string_nine",
					"db_type": "VARCHAR(1000)",
					"default": "'abcdefgh'",
					"comment": "",
					"nullable": false,
					"generated": false,
					"autoincr": false,
					"domain_name": "",
					"type": "string"
				},
				{
					"name": "string_ten",
					"db_type": "VARCHAR(1000)",
					"default": "''",
					"comment": "",
					"nullable": true,
					"generated": false,
					"autoincr": false,
					"domain_name": "",
					"type": "string"
				},
				{
					"name": "string_eleven",
					"db_type": "VARCHAR(1000)",
					"default": "''",
					"comment": "",
					"nullable": false,
					"generated": false,
					"autoincr": false,
					"domain_name": "",
					"type": "string"
				},
				{
					"name": "big_int_zero",
					"db_type": "BIGINT",
					"default": "NULL",
					"comment": "",
					"nullable": true,
					"generated": false,
					"autoincr": false,
					"domain_name": "",
					"type": "int64"
				},
				{
					"name": "big_int_one",
					"db_type": "BIGINT",
					"default": "NULL",
					"comment": "",
					"nullable": true,
					"generated": false,
					"autoincr": false,
					"domain_name": "",
					"type": "int64"
				},
				{
					"name": "big_int_two",
					"db_type": "BIGINT",
					"default": "",
					"comment": "",
					"nullable": false,
					"generated": false,
					"autoincr": false,
					"domain_name": "",
					"type": "int64"
				},
				{
					"name": "big_int_three",
					"db_type": "BIGINT",
					"default": "111111",
					"comment": "",
					"nullable": true,
					"generated": false,
					"autoincr": false,
					"domain_name": "",
					"type": "int64"
				},
				{
					"name": "big_int_four",
					"db_type": "BIGINT",
					"default": "222222",
					"comment": "",
					"nullable": false,
					"generated": false,
					"autoincr": false,
					"domain_name": "",
					"type": "int64"
				},
				{
					"name": "big_int_five",
					"db_type": "BIGINT",
					"default": "0",
					"comment": "",
					"nullable": true,
					"generated": false,
					"autoincr": false,
					"domain_name": "",
					"type": "int64"
				},
				{
					"name": "big_int_six",
					"db_type": "BIGINT",
					"default": "0",
					"comment": "",
					"nullable": false,
					"generated": false,
					"autoincr": false,
					"domain_name": "",
					"type": "int64"
				},
				{
					"name": "int_zero",
					"db_type": "INT",
					"default": "NULL",
					"comment": "",
					"nullable": true,
					"generated": false,
					"autoincr": false,
					"domain_name": "",
					"type": "int32"
				},
				{
					"name": "int_one",
					"db_type": "INT",
					"default": "NULL",
					"comment": "",
					"nullable": true,
					"generated": false,
					"autoincr": false,
					"domain_name": "",
					"type": "int32"
				},
				{
					"name": "int_two",
					"db_type": "INT",
					"default": "",
					"comment": "",
					"nullable": false,
					"generated": false,
					"autoincr": false,
					"domain_name": "",
					"type": "int32"
				},
				{
					"name": "int_three",
					"db_type": "INT",
					"default": "333333",
					"comment": "",
					"nullable": true,
					"generated": false,
					"autoincr": false,
					"domain_name": "",
					"type": "int32"
				},
				{
					"name": "int_four",
					"db_type": "INT",
					"default": "444444",
					"comment": "",
					"nullable": false,
					"generated": false,
					"autoincr": false,
					"domain_name": "",
					"type": "int32"
				},
				{
					"name": "int_five",
					"db_type": "INT",
					"default": "0",
					"comment": "",
					"nullable": true,
					"generated": false,
					"autoincr": false,
					"domain_name": "",
					"type": "int32"
				},
				{
					"name": "int_six",
					"db_type": "INT",
					"default": "0",
					"comment": "",
					"nullable": false,
					"generated": false,
					"autoincr": false,
					"domain_name": "",
					"type": "int32"
				},
				{
					"name": "float_zero",
					"db_type": "FLOAT",
					"default": "NULL",
					"comment": "",
					"nullable": true,
					"generated": false,
					"autoincr": false,
					"domain_name": "",
					"type": "float32"
				},
				{
					"name": "float_one",
					"db_type": "FLOAT",
					"default": "NULL",
					"comment": "",
					"nullable": true,
					"generated": false,
					"autoincr": false,
					"domain_name": "",
					"type": "float32"
				},
				{
					"name": "float_two",
					"db_type": "FLOAT(2,1)",
					"default": "NULL",
					"comment": "",
					"nullable": true,
					"generated": false,
					"autoincr": false,
					"domain_name": "",
					"type": "string"
				},
				{
					"name": "float_three",
					"db_type": "FLOAT(2,1)",
					"default": "NULL",
					"comment": "",
					"nullable": true,
					"generated": false,
					"autoincr": false,
					"domain_name": "",
					"type": "string"
				},
				{
					"name": "float_four",
					"db_type": "FLOAT(2,1)",
					"default": "NULL",
					"comment": "",
					"nullable": true,
					"generated": false,
					"autoincr": false,
					"domain_name": "",
					"type": "string"
				},
				{
					"name": "float_five",
					"db_type": "FLOAT(2,1)",
					"default": "",
					"comment": "",
					"nullable": false,
					"generated": false,
					"autoincr": false,
					"domain_name": "",
					"type": "string"
				},
				{
					"name": "float_six",
					"db_type": "FLOAT(2,1)",
					"default": "1.1",
					"comment": "",
					"nullable": true,
					"generated": false,
					"autoincr": false,
					"domain_name": "",
					"type": "string"
				},
				{
					"name": "float_seven",
					"db_type": "FLOAT(2,1)",
					"default": "1.1",
					"comment": "",
					"nullable": false,
					"generated": false,
					"autoincr": false,
					"domain_name": "",
					"type": "string"
				},
				{
					"name": "float_eight",
					"db_type": "FLOAT(2,1)",
					"default": "0.0",
					"comment": "",
					"nullable": true,
					"generated": false,
					"autoincr": false,
					"domain_name": "",
					"type": "string"
				},
				{
					"name": "float_nine",
					"db_type": "FLOAT(2,1)",
					"default": "0.0",
					"comment": "",
					"nullable": true,
					"generated": false,
					"autoincr": false,
					"domain_name": "",
					"type": "string"
				},
				{
					"name": "bytea_zero",
					"db_type": "BINARY",
					"default": "NULL",
					"comment": "",
					"nullable": true,
					"generated": false,
					"autoincr": false,
					"domain_name": "",
					"type": "string"
				},
				{
					"name": "bytea_one",
					"db_type": "BINARY",
					"default": "NULL",
					"comment": "",
					"nullable": true,
					"generated": false,
					"autoincr": false,
					"domain_name": "",
					"type": "string"
				},
				{
					"name": "bytea_two",
					"db_type": "BINARY",
					"default": "",
					"comment": "",
					"nullable": false,
					"generated": false,
					"autoincr": false,
					"domain_name": "",
					"type": "string"
				},
				{
					"name": "bytea_three",
					"db_type": "BINARY",
					"default": "'a'",
					"comment": "",
					"nullable": false,
					"generated": false,
					"autoincr": false,
					"domain_name": "",
					"type": "string"
				},
				{
					"name": "bytea_four",
					"db_type": "BINARY",
					"default": "'b'",
					"comment": "",
					"nullable": true,
					"generated": false,
					"autoincr": false,
					"domain_name": "",
					"type": "string"
				},
				{
					"name": "bytea_five",
					"db_type": "BINARY(100)",
					"default": "'abcdefghabcdefghabcdefgh'",
					"comment": "",
					"nullable": false,
					"generated": false,
					"autoincr": false,
					"domain_name": "",
					"type": "string"
				},
				{
					"name": "bytea_six",
					"db_type": "BINARY(100)",
					"default": "'hgfedcbahgfedcbahgfedcba'",
					"comment": "",
					"nullable": true,
					"generated": false,
					"autoincr": false,
					"domain_name": "",
					"type": "string"
				},
				{
					"name": "bytea_seven",
					"db_type": "BINARY",
					"default": "''",
					"comment": "",
					"nullable": false,
					"generated": false,
					"autoincr": false,
					"domain_name": "",
					"type": "string"
				},
				{
					"name": "bytea_eight",
					"db_type": "BINARY",
					"default": "''",
					"comment": "",
					"nullable": false,
					"generated": false,
					"autoincr": false,
					"domain_name": "",
					"type": "string"
				},
				{
					"name": "time_zero",
					"db_type": "TIMESTAMP",
					"default": "NULL",
					"comment": "",
					"nullable": true,
					"generated": false,
					"autoincr": false,
					"domain_name": "",
					"type": "string"
				},
				{
					"name": "time_one",
					"db_type": "DATE",
					"default": "NULL",
					"comment": "",
					"nullable": true,
					"generated": false,
					"autoincr": false,
					"domain_name": "",
					"type": "time.Time"
				},
				{
					"name": "time_two",
					"db_type": "TIMESTAMP",
					"default": "null",
					"comment": "",
					"nullable": true,
					"generated": false,
					"autoincr": false,
					"domain_name": "",
					"type": "string"
				},
				{
					"name": "time_three",
					"db_type": "TIMESTAMP",
					"default": "NULL",
					"comment": "",
					"nullable": true,
					"generated": false,
					"autoincr": false,
					"domain_name": "",
					"type": "string"
				},
				{
					"name": "time_five",
					"db_type": "TIMESTAMP",
					"default": "current_timestamp",
					"comment": "",
					"nullable": true,
					"generated": false,
					"autoincr": false,
					"domain_name": "",
					"type": "string"
				},
				{
					"name": "time_nine",
					"db_type": "TIMESTAMP",
					"default": "current_timestamp",
					"comment": "",
					"nullable": false,
					"generated": false,
					"autoincr": false,
					"domain_name": "",
					"type": "string"
				},
				{
					"name": "time_eleven",
					"db_type": "DATE",
					"default": "NULL",
					"comment": "",
					"nullable": true,
					"generated": false,
					"autoincr": false,
					"domain_name": "",
					"type": "time.Time"
				},
				{
					"name": "time_twelve",
					"db_type": "DATE",
					"default": "",
					"comment": "",
					"nullable": false,
					"generated": false,
					"autoincr": false,
					"domain_name": "",
					"type": "time.Time"
				},
				{
					"name": "time_fifteen",
					"db_type": "DATE",
					"default": "'19990108'",
					"comment": "",
					"nullable": true,
					"generated": false,
					"autoincr": false,
					"domain_name": "",
					"type": "time.Time"
				},
				{
					"name": "time_sixteen",
					"db_type": "DATE",
					"default": "'1999-01-08'",
					"comment": "",
					"nullable": false,
					"generated": false,
					"autoincr": false,
					"domain_name": "",
					"type": "time.Time"
				},
				{
					"name": "json_null",
					"db_type": "JSON",
					"default": "NULL",
					"comment": "",
					"nullable": true,
					"generated": false,
					"autoincr": false,
					"domain_name": "",
					"type": "types.JSON[json.RawMessage]"
				},
				{
					"name": "json_nnull",
					"db_type": "JSON",
					"default": "",
					"comment": "",
					"nullable": false,
					"generated": false,
					"autoincr": false,
					"domain_name": "",
					"type": "types.JSON[json.RawMessage]"
				},
				{
					"name": "tinyint_null",
					"db_type": "TINYINT",
					"default": "NULL",
					"comment": "",
					"nullable": true,
					"generated": false,
					"autoincr": false,
					"domain_name": "",
					"type": "int8"
				},
				{
					"name": "tinyint_nnull",
					"db_type": "TINYINT",
					"default": "",
					"comment": "",
					"nullable": false,
					"generated": false,
					"autoincr": false,
					"domain_name": "",
					"type": "int8"
				},
				{
					"name": "tinyint1_null",
					"db_type": "TINYINT(1)",
					"default": "NULL",
					"comment": "",
					"nullable": true,
					"generated": false,
					"autoincr": false,
					"domain_name": "",
					"type": "string"
				},
				{
					"name": "tinyint1_nnull",
					"db_type": "TINYINT(1)",
					"default": "",
					"comment": "",
					"nullable": false,
					"generated": false,
					"autoincr": false,
					"domain_name": "",
					"type": "string"
				},
				{
					"name": "tinyint2_null",
					"db_type": "TINYINT(2)",
					"default": "NULL",
					"comment": "",
					"nullable": true,
					"generated": false,
					"autoincr": false,
					"domain_name": "",
					"type": "string"
				},
				{
					"name": "tinyint2_nnull",
					"db_type": "TINYINT(2)",
					"default": "",
					"comment": "",
					"nullable": false,
					"generated": false,
					"autoincr": false,
					"domain_name": "",
					"type": "string"
				},
				{
					"name": "smallint_null",
					"db_type": "SMALLINT",
					"default": "NULL",
					"comment": "",
					"nullable": true,
					"generated": false,
					"autoincr": false,
					"domain_name": "",
					"type": "int16"
				},
				{
					"name": "smallint_nnull",
					"db_type": "SMALLINT",
					"default": "",
					"comment": "",
					"nullable": false,
					"generated": false,
					"autoincr": false,
					"domain_name": "",
					"type": "int16"
				},
				{
					"name": "mediumint_null",
					"db_type": "MEDIUMINT",
					"default": "NULL",
					"comment": "",
					"nullable": true,
					"generated": false,
					"autoincr": false,
					"domain_name": "",
					"type": "int32"
				},
				{
					"name": "mediumint_nnull",
					"db_type": "MEDIUMINT",
					"default": "",
					"comment": "",
					"nullable": false,
					"generated": false,
					"autoincr": false,
					"domain_name": "",
					"type": "int32"
				},
				{
					"name": "bigint_null",
					"db_type": "BIGINT",
					"default": "NULL",
					"comment": "",
					"nullable": true,
					"generated": false,
					"autoincr": false,
					"domain_name": "",
					"type": "int64"
				},
				{
					"name": "bigint_nnull",
					"db_type": "BIGINT",
					"default": "",
					"comment": "",
					"nullable": false,
					"generated": false,
					"autoincr": false,
					"domain_name": "",
					"type": "int64"
				},
				{
					"name": "float_null",
					"db_type": "FLOAT",
					"default": "NULL",
					"comment": "",
					"nullable": true,
					"generated": false,
					"autoincr": false,
					"domain_name": "",
					"type": "float32"
				},
				{
					"name": "float_nnull",
					"db_type": "FLOAT",
					"default": "",
					"comment": "",
					"nullable": false,
					"generated": false,
					"autoincr": false,
					"domain_name": "",
					"type": "float32"
				},
				{
					"name": "double_null",
					"db_type": "DOUBLE",
					"default": "NULL",
					"comment": "",
					"nullable": true,
					"generated": false,
					"autoincr": false,
					"domain_name": "",
					"type": "float64"
				},
				{
					"name": "double_nnull",
					"db_type": "DOUBLE",
					"default": "",
					"comment": "",
					"nullable": false,
					"generated": false,
					"autoincr": false,
					"domain_name": "",
					"type": "float64"
				},
				{
					"name": "doubleprec_null",
					"db_type": "DOUBLE PRECISION",
					"default": "NULL",
					"comment": "",
					"nullable": true,
					"generated": false,
					"autoincr": false,
					"domain_name": "",
					"type": "float64"
				},
				{
					"name": "doubleprec_nnull",
					"db_type": "DOUBLE PRECISION",
					"default": "",
					"comment": "",
					"nullable": false,
					"generated": false,
					"autoincr": false,
					"domain_name": "",
					"type": "float64"
				},
				{
					"name": "real_null",
					"db_type": "REAL",
					"default": "NULL",
					"comment": "",
					"nullable": true,
					"generated": false,
					"autoincr": false,
					"domain_name": "",
					"type": "float32"
				},
				{
					"name": "real_nnull",
					"db_type": "REAL",
					"default": "",
					"comment": "",
					"nullable": false,
					"generated": false,
					"autoincr": false,
					"domain_name": "",
					"type": "float32"
				},
				{
					"name": "boolean_null",
					"db_type": "BOOLEAN",
					"default": "NULL",
					"comment": "",
					"nullable": true,
					"generated": false,
					"autoincr": false,
					"domain_name": "",
					"type": "bool"
				},
				{
					"name": "boolean_nnull",
					"db_type": "BOOLEAN",
					"default": "",
					"comment": "",
					"nullable": false,
					"generated": false,
					"autoincr": false,
					"domain_name": "",
					"type": "bool"
				},
				{
					"name": "date_null",
					"db_type": "DATE",
					"default": "NULL",
					"comment": "",
					"nullable": true,
					"generated": false,
					"autoincr": false,
					"domain_name": "",
					"type": "time.Time"
				},
				{
					"name": "date_nnull",
					"db_type": "DATE",
					"default": "",
					"comment": "",
					"nullable": false,
					"generated": false,
					"autoincr": false,
					"domain_name": "",
					"type": "time.Time"
				},
				{
					"name": "datetime_null",
					"db_type": "DATETIME",
					"default": "NULL",
					"comment": "",
					"nullable": true,
					"generated": false,
					"autoincr": false,
					"domain_name": "",
					"type": "time.Time"
				},
				{
					"name": "datetime_nnull",
					"db_type": "DATETIME",
					"default": "",
					"comment": "",
					"nullable": false,
					"generated": false,
					"autoincr": false,
					"domain_name": "",
					"type": "time.Time"
				},
				{
					"name": "timestamp_null",
					"db_type": "TIMESTAMP",
					"default": "NULL",
					"comment": "",
					"nullable": true,
					"generated": false,
					"autoincr": false,
					"domain_name": "",
					"type": "string"
				},
				{
					"name": "timestamp_nnull",
					"db_type": "TIMESTAMP",
					"default": "current_timestamp",
					"comment": "",
					"nullable": false,
					"generated": false,
					"autoincr": false,
					"domain_name": "",
					"type": "string"
				},
				{
					"name": "binary_null",
					"db_type": "BINARY",
					"default": "NULL",
					"comment": "",
					"nullable": true,
					"generated": false,
					"autoincr": false,
					"domain_name": "",
					"type": "string"
				},
				{
					"name": "binary_nnull",
					"db_type": "BINARY",
					"default": "",
					"comment": "",
					"nullable": false,
					"generated": false,
					"autoincr": false,
					"domain_name": "",
					"type": "string"
				},
				{
					"name": "varbinary_null",
					"db_type": "VARBINARY(100)",
					"default": "NULL",
					"comment": "",
					"nullable": true,
					"generated": false,
					"autoincr": false,
					"domain_name": "",
					"type": "string"
				},
				{
					"name": "varbinary_nnull",
					"db_type": "VARBINARY(100)",
					"default": "",
					"comment": "",
					"nullable": false,
					"generated": false,
					"autoincr": false,
					"domain_name": "",
					"type": "string"
				},
				{
					"name": "tinyblob_null",
					"db_type": "TINYBLOB",
					"default": "NULL",
					"comment": "",
					"nullable": true,
					"generated": false,
					"autoincr": false,
					"domain_name": "",
					"type": "string"
				},
				{
					"name": "tinyblob_nnull",
					"db_type": "TINYBLOB",
					"default": "",
					"comment": "",
					"nullable": false,
					"generated": false,
					"autoincr": false,
					"domain_name": "",
					"type": "string"
				},
				{
					"name": "blob_null",
					"db_type": "BLOB",
					"default": "NULL",
					"comment": "",
					"nullable": true,
					"generated": false,
					"autoincr": false,
					"domain_name": "",
					"type": "[]byte"
				},
				{
					"name": "blob_nnull",
					"db_type": "BLOB",
					"default": "",
					"comment": "",
					"nullable": false,
					"generated": false,
					"autoincr": false,
					"domain_name": "",
					"type": "[]byte"
				},
				{
					"name": "mediumblob_null",
					"db_type": "MEDIUMBLOB",
					"default": "NULL",
					"comment": "",
					"nullable": true,
					"generated": false,
					"autoincr": false,
					"domain_name": "",
					"type": "string"
				},
				{
					"name": "mediumblob_nnull",
					"db_type": "MEDIUMBLOB",
					"default": "",
					"comment": "",
					"nullable": false,
					"generated": false,
					"autoincr": false,
					"domain_name": "",
					"type": "string"
				},
				{
					"name": "longblob_null",
					"db_type": "LONGBLOB",
					"default": "NULL",
					"comment": "",
					"nullable": true,
					"generated": false,
					"autoincr": false,
					"domain_name": "",
					"type": "string"
				},
				{
					"name": "longblob_nnull",
					"db_type": "LONGBLOB",
					"default": "",
					"comment": "",
					"nullable": false,
					"generated": false,
					"autoincr": false,
					"domain_name": "",
					"type": "string"
				},
				{
					"name": "varchar_null",
					"db_type": "VARCHAR(100)",
					"default": "NULL",
					"comment": "",
					"nullable": true,
					"generated": false,
					"autoincr": false,
					"domain_name": "",
					"type": "string"
				},
				{
					"name": "varchar_nnull",
					"db_type": "VARCHAR(100)",
					"default": "",
					"comment": "",
					"nullable": false,
					"generated": false,
					"autoincr": false,
					"domain_name": "",
					"type": "string"
				},
				{
					"name": "char_null",
					"db_type": "CHAR",
					"default": "NULL",
					"comment": "",
					"nullable": true,
					"generated": false,
					"autoincr": false,
					"domain_name": "",
					"type": "string"
				},
				{
					"name": "char_nnull",
					"db_type": "CHAR",
					"default": "",
					"comment": "",
					"nullable": false,
					"generated": false,
					"autoincr": false,
					"domain_name": "",
					"type": "string"
				},
				{
					"name": "text_null",
					"db_type": "TEXT",
					"default": "NULL",
					"comment": "",
					"nullable": true,
					"generated": false,
					"autoincr": false,
					"domain_name": "",
					"type": "string"
				},
				{
					"name": "text_nnull",
					"db_type": "TEXT",
					"default": "",
					"comment": "",
					"nullable": false,
					"generated": false,
					"autoincr": false,
					"domain_name": "",
					"type": "string"
				}
			],
			"constraints": {
				"primary": {
					"name": "pk_main_type_monsters",
					"columns": [
						"id"
					]
				},
				"foreign": [],
				"uniques": []
			}
		},
		{
			"key": "user_videos",
			"schema": "",
			"name": "user_videos",
			"columns": [
				{
					"name": "user_id",
					"db_type": "INT",
					"default": "NULL",
					"comment": "",
					"nullable": true,
					"generated": false,
					"autoincr": false,
					"domain_name": "",
					"type": "int32"
				},
				{
					"name": "video_id",
					"db_type": "INT",
					"default": "NULL",
					"comment": "",
					"nullable": true,
					"generated": false,
					"autoincr": false,
					"domain_name": "",
					"type": "int32"
				},
				{
					"name": "sponsor_id",
					"db_type": "INT",
					"default": "NULL",
					"comment": "",
					"nullable": true,
					"generated": false,
					"autoincr": false,
					"domain_name": "",
					"type": "int32"
				}
			],
			"constraints": {
				"primary": null,
				"foreign": [],
				"uniques": []
			}
		},
		{
			"key": "users",
			"schema": "",
			"name": "users",
			"columns": [
				{
					"name": "id",
					"db_type": "INT",
					"default": "",
					"comment": "",
					"nullable": false,
					"generated": false,
					"autoincr": false,
					"domain_name": "",
					"type": "int32"
				}
			],
			"constraints": {
				"primary": {
					"name": "pk_main_users",
					"columns": [
						"id"
					]
				},
				"foreign": [],
				"uniques": []
			}
		},
		{
			"key": "video_tags",
			"schema": "",
			"name": "video_tags",
			"columns": [
				{
					"name": "video_id",
					"db_type": "INT",
					"default": "",
					"comment": "",
					"nullable": false,
					"generated": false,
					"autoincr": false,
					"domain_name": "",
					"type": "int32"
				},
				{
					"name": "tag_id",
					"db_type": "INT",
					"default": "",
					"comment": "",
					"nullable": false,
					"generated": false,
					"autoincr": false,
					"domain_name": "",
					"type": "int32"
				}
			],
			"constraints": {
				"primary": {
					"name": "pk_main_video_tags",
					"columns": [
						"video_id",
						"tag_id"
					]
				},
				"foreign": [
					{
						"name": "fk_video_tags_0",
						"columns": [
							"tag_id"
						],
						"foreign_table": "tags",
						"foreign_columns": [
							"id"
						]
					},
					{
						"name": "fk_video_tags_1",
						"columns": [
							"video_id"
						],
						"foreign_table": "videos",
						"foreign_columns": [
							"id"
						]
					}
				],
				"uniques": []
			}
		},
		{
			"key": "videos",
			"schema": "",
			"name": "videos",
			"columns": [
				{
					"name": "id",
					"db_type": "INT",
					"default": "",
					"comment": "",
					"nullable": false,
					"generated": false,
					"autoincr": false,
					"domain_name": "",
					"type": "int32"
				},
				{
					"name": "user_id",
					"db_type": "INT",
					"default": "",
					"comment": "",
					"nullable": false,
					"generated": false,
					"autoincr": false,
					"domain_name": "",
					"type": "int32"
				},
				{
					"name": "sponsor_id",
					"db_type": "INT",
					"default": "NULL",
					"comment": "",
					"nullable": true,
					"generated": false,
					"autoincr": false,
					"domain_name": "",
					"type": "int32"
				}
			],
			"constraints": {
				"primary": {
					"name": "pk_main_videos",
					"columns": [
						"id"
					]
				},
				"foreign": [
					{
						"name": "fk_videos_0",
						"columns": [
							"sponsor_id"
						],
						"foreign_table": "sponsors",
						"foreign_columns": [
							"id"
						]
					},
					{
						"name": "fk_videos_1",
						"columns": [
							"user_id"
						],
						"foreign_table": "users",
						"foreign_columns": [
							"id"
						]
					}
				],
				"uniques": [
					{
						"name": "sqlite_autoindex_videos_2",
						"columns": [
							"sponsor_id"
						]
					}
				]
			}
		}
	],
	"enums": null,
	"extra_info": null
}